AerozOff/__init__.py
AerozOff-0.0.1.dist-info/DESCRIPTION.rst
AerozOff-0.0.1.dist-info/METADATA
AerozOff-0.0.1.dist-info/RECORD
AerozOff-0.0.1.dist-info/WHEEL
AerozOff-0.0.1.dist-info/metadata.json
AerozOff-0.0.1.dist-info/top_level.txt
oimbot/__init__.py
