Metadata-Version: 2.0
Name: AerozOff
Version: 0.0.1
Summary: Lobby bot.
Home-page: https://www.youtube.com/
Author: Aeroz
Author-email: UNKNOWN
License: UNKNOWN
Platform: UNKNOWN
Classifier: Programming Language :: Python :: 3
Classifier: License :: OSI Approved :: MIT License
Classifier: Operating System :: OS Independent
Requires-Dist: BenBotAsync
Requires-Dist: FortniteAPIAsync
Requires-Dist: aiohttp
Requires-Dist: colorama
Requires-Dist: crayons
Requires-Dist: fortnitepy
Requires-Dist: sanic (==21.6.2)
